kavo/__init__.py
kavo/_client.py
kavo/_config.py
kavo/_db.py
kavo/_labels.py
kavo/_models.py
kavo/_pack.py
kavo/_types_.pyi
kavo/_utils.py
kavo-0.4.0.dist-info/licenses/LICENSE
kavo-0.4.0.dist-info/METADATA
kavo-0.4.0.dist-info/WHEEL
kavo-0.4.0.dist-info/top_level.txt
kavo-0.4.0.dist-info/RECORD
