Metadata-Version: 2.4
Name: kavo
Version: 0.4.0
Summary: Key-value storage on top of LMDB for storing HTTP entries
Requires-Python: >=3.9
License-File: LICENSE
Requires-Dist: lmdb>=1.6.2
Requires-Dist: msgpack>=1.1.1
Provides-Extra: async
Requires-Dist: anyio>=4.9.0; extra == "async"
Dynamic: license-file
